colorsname/__init__.py
colorsname/_colorsname.py
colorsname/color.json
colorsname-1.0.1.dist-info/METADATA
colorsname-1.0.1.dist-info/WHEEL
colorsname-1.0.1.dist-info/top_level.txt
colorsname-1.0.1.dist-info/RECORD
