Metadata-Version: 2.1
Name: colorsname
Version: 1.0.1
Summary: colors' names.
Home-page: https://github.com/userElaina
Author: userElaina
Author-email: userElaina@google.com
License: UNKNOWN
Keywords: color name elaina
Platform: UNKNOWN
Classifier: Programming Language :: Python :: 3
Requires-Python: >=3.6
